{"match_id": 5690297880, "barracks_status_dire": 63, "barracks_status_radiant": 3, "chat": null, "cluster": 123, "cosmetics": null, "dire_score": 54, "dire_team_id": null, "draft_timings": null, "duration": 2360, "engine": 1, "first_blood_time": 50, "game_mode": 22, "human_players": 10, "leagueid": 0, "lobby_type": 7, "match_seq_num": 4784991882, "negative_votes": 0, "objectives": null, "picks_bans": [{"is_pick": true, "hero_id": 108, "team": 0, "order": 0}, {"is_pick": true, "hero_id": 27, "team": 1, "order": 1}, {"is_pick": true, "hero_id": 66, "team": 0, "order": 2}, {"is_pick": true, "hero_id": 97, "team": 1, "order": 3}, {"is_pick": true, "hero_id": 67, "team": 0, "order": 4}, {"is_pick": true, "hero_id": 22, "team": 1, "order": 5}, {"is_pick": true, "hero_id": 86, "team": 0, "order": 6}, {"is_pick": true, "hero_id": 85, "team": 1, "order": 7}, {"is_pick": true, "hero_id": 41, "team": 1, "order": 8}, {"is_pick": true, "hero_id": 35, "team": 0, "order": 9}, {"is_pick": false, "hero_id": 114, "team": 0, "order": 10}, {"is_pick": false, "hero_id": 1, "team": 0, "order": 11}, {"is_pick": false, "hero_id": 32, "team": 0, "order": 12}, {"is_pick": false, "hero_id": 2, "team": 0, "order": 13}], "positive_votes": 0, "radiant_gold_adv": null, "radiant_score": 22, "radiant_team_id": null, "radiant_win": false, "radiant_xp_adv": null, "skill": 1, "start_time": 1604721960, "teamfights": null, "tower_status_dire": 2038, "tower_status_radiant": 0, "version": null, "players": [{"match_id": 5690297880, "player_slot": 0, "ability_targets": null, "ability_upgrades_arr": null, "ability_uses": null, "account_id": 870962873, "actions": null, "additional_units": null, "assists": 10, "backpack_0": 216, "backpack_1": 0, "backpack_2": 0, "backpack_3": null, "buyback_log": null, "camps_stacked": null, "connection_log": null, "creeps_stacked": null, "damage": null, "damage_inflictor": null, "damage_inflictor_received": null, "damage_taken": null, "damage_targets": null, "deaths": 15, "denies": 10, "dn_t": null, "firstblood_claimed": null, "gold": null, "gold_per_min": 291, "gold_reasons": null, "gold_spent": null, "gold_t": null, "hero_damage": null, "hero_healing": null, "hero_hits": null, "hero_id": 108, "item_0": 180, "item_1": 127, "item_2": 79, "item_3": 131, "item_4": 94, "item_5": 36, "item_neutral": 359, "item_uses": null, "kill_streaks": null, "killed": null, "killed_by": null, "kills": 1, "kills_log": null, "lane_pos": null, "last_hits": 110, "leaver_status": 0, "level": 17, "lh_t": null, "life_state": null, "max_hero_hit": null, "multi_kills": null, "net_worth": 9156, "obs": null, "obs_left_log": null, "obs_log": null, "obs_placed": null, "party_id": null, "party_size": null, "performance_others": null, "permanent_buffs": null, "pings": null, "pred_vict": null, "purchase": null, "purchase_log": null, "randomed": null, "repicked": null, "roshans_killed": null, "rune_pickups": null, "runes": null, "runes_log": null, "sen": null, "sen_left_log": null, "sen_log": null, "sen_placed": null, "stuns": null, "teamfight_participation": null, "times": null, "tower_damage": null, "towers_killed": null, "xp_per_min": 378, "xp_reasons": null, "xp_t": null, "personaname": "BE NICE", "name": null, "last_login": "2018-04-24T01:16:48.288Z", "radiant_win": false, "start_time": 1604721960, "duration": 2360, "cluster": 123, "lobby_type": 7, "game_mode": 22, "is_contributor": false, "patch": 46, "region": 2, "isRadiant": true, "win": 0, "lose": 1, "total_gold": 11446, "total_xp": 14868, "kills_per_min": 0.02542372881355932, "kda": 0, "abandons": 0, "rank_tier": 33, "is_subscriber": false, "cosmetics": [], "benchmarks": {"gold_per_min": {"raw": 291, "pct": 0}, "xp_per_min": {"raw": 378, "pct": 0}, "kills_per_min": {"raw": 0.02542372881355932, "pct": 0.08333333333333333}, "last_hits_per_min": {"raw": 2.7966101694915255, "pct": 0}, "hero_damage_per_min": {"raw": 0, "pct": 0}, "hero_healing_per_min": {"raw": 0, "pct": 0.5833333333333334}, "tower_damage": {}, "stuns_per_min": {"raw": 0, "pct": 0}, "lhten": {}}}, {"match_id": 5690297880, "player_slot": 1, "ability_targets": null, "ability_upgrades_arr": null, "ability_uses": null, "account_id": 39336713, "actions": null, "additional_units": null, "assists": 9, "backpack_0": 11, "backpack_1": 27, "backpack_2": 0, "backpack_3": null, "buyback_log": null, "camps_stacked": null, "connection_log": null, "creeps_stacked": null, "damage": null, "damage_inflictor": null, "damage_inflictor_received": null, "damage_taken": null, "damage_targets": null, "deaths": 11, "denies": 12, "dn_t": null, "firstblood_claimed": null, "gold": null, "gold_per_min": 344, "gold_reasons": null, "gold_spent": null, "gold_t": null, "hero_damage": null, "hero_healing": null, "hero_hits": null, "hero_id": 67, "item_0": 8, "item_1": 63, "item_2": 185, "item_3": 17, "item_4": 147, "item_5": 75, "item_neutral": 355, "item_uses": null, "kill_streaks": null, "killed": null, "killed_by": null, "kills": 4, "kills_log": null, "lane_pos": null, "last_hits": 170, "leaver_status": 0, "level": 17, "lh_t": null, "life_state": null, "max_hero_hit": null, "multi_kills": null, "net_worth": 11067, "obs": null, "obs_left_log": null, "obs_log": null, "obs_placed": null, "party_id": null, "party_size": null, "performance_others": null, "permanent_buffs": null, "pings": null, "pred_vict": null, "purchase": null, "purchase_log": null, "randomed": null, "repicked": null, "roshans_killed": null, "rune_pickups": null, "runes": null, "runes_log": null, "sen": null, "sen_left_log": null, "sen_log": null, "sen_placed": null, "stuns": null, "teamfight_participation": null, "times": null, "tower_damage": null, "towers_killed": null, "xp_per_min": 359, "xp_reasons": null, "xp_t": null, "personaname": "Three6Travis", "name": null, "last_login": null, "radiant_win": false, "start_time": 1604721960, "duration": 2360, "cluster": 123, "lobby_type": 7, "game_mode": 22, "is_contributor": false, "patch": 46, "region": 2, "isRadiant": true, "win": 0, "lose": 1, "total_gold": 13530, "total_xp": 14120, "kills_per_min": 0.10169491525423728, "kda": 1, "abandons": 0, "rank_tier": 55, "is_subscriber": false, "cosmetics": [], "benchmarks": {"gold_per_min": {"raw": 344, "pct": 0.05555555555555555}, "xp_per_min": {"raw": 359, "pct": 0.05555555555555555}, "kills_per_min": {"raw": 0.10169491525423728, "pct": 0.1388888888888889}, "last_hits_per_min": {"raw": 4.322033898305085, "pct": 0.05555555555555555}, "hero_damage_per_min": {"raw": 0, "pct": 0}, "hero_healing_per_min": {"raw": 0, "pct": 1}, "tower_damage": {}, "stuns_per_min": {"raw": 0, "pct": 0.6111111111111112}, "lhten": {}}}, {"match_id": 5690297880, "player_slot": 2, "ability_targets": null, "ability_upgrades_arr": null, "ability_uses": null, "account_id": 236793638, "actions": null, "additional_units": null, "assists": 11, "backpack_0": 0, "backpack_1": 0, "backpack_2": 0, "backpack_3": null, "buyback_log": null, "camps_stacked": null, "connection_log": null, "creeps_stacked": null, "damage": null, "damage_inflictor": null, "damage_inflictor_received": null, "damage_taken": null, "damage_targets": null, "deaths": 10, "denies": 0, "dn_t": null, "firstblood_claimed": null, "gold": null, "gold_per_min": 265, "gold_reasons": null, "gold_spent": null, "gold_t": null, "hero_damage": null, "hero_healing": null, "hero_hits": null, "hero_id": 66, "item_0": 187, "item_1": 254, "item_2": 188, "item_3": 231, "item_4": 34, "item_5": 218, "item_neutral": 361, "item_uses": null, "kill_streaks": null, "killed": null, "killed_by": null, "kills": 3, "kills_log": null, "lane_pos": null, "last_hits": 75, "leaver_status": 0, "level": 14, "lh_t": null, "life_state": null, "max_hero_hit": null, "multi_kills": null, "net_worth": 8741, "obs": null, "obs_left_log": null, "obs_log": null, "obs_placed": null, "party_id": null, "party_size": null, "performance_others": null, "permanent_buffs": null, "pings": null, "pred_vict": null, "purchase": null, "purchase_log": null, "randomed": null, "repicked": null, "roshans_killed": null, "rune_pickups": null, "runes": null, "runes_log": null, "sen": null, "sen_left_log": null, "sen_log": null, "sen_placed": null, "stuns": null, "teamfight_participation": null, "times": null, "tower_damage": null, "towers_killed": null, "xp_per_min": 278, "xp_reasons": null, "xp_t": null, "personaname": "SURVIVOR OF PERU", "name": null, "last_login": null, "radiant_win": false, "start_time": 1604721960, "duration": 2360, "cluster": 123, "lobby_type": 7, "game_mode": 22, "is_contributor": false, "patch": 46, "region": 2, "isRadiant": true, "win": 0, "lose": 1, "total_gold": 10423, "total_xp": 10934, "kills_per_min": 0.07627118644067796, "kda": 1, "abandons": 0, "rank_tier": 54, "is_subscriber": false, "cosmetics": [], "benchmarks": {"gold_per_min": {"raw": 265, "pct": 0.75}, "xp_per_min": {"raw": 278, "pct": 0.25}, "kills_per_min": {"raw": 0.07627118644067796, "pct": 0.75}, "last_hits_per_min": {"raw": 1.906779661016949, "pct": 0.75}, "hero_damage_per_min": {"raw": 0, "pct": 0}, "hero_healing_per_min": {"raw": 0, "pct": 0}, "tower_damage": {}, "stuns_per_min": {"raw": 0, "pct": 0}, "lhten": {}}}, {"match_id": 5690297880, "player_slot": 3, "ability_targets": null, "ability_upgrades_arr": null, "ability_uses": null, "account_id": null, "actions": null, "additional_units": null, "assists": 4, "backpack_0": 0, "backpack_1": 0, "backpack_2": 0, "backpack_3": null, "buyback_log": null, "camps_stacked": null, "connection_log": null, "creeps_stacked": null, "damage": null, "damage_inflictor": null, "damage_inflictor_received": null, "damage_taken": null, "damage_targets": null, "deaths": 12, "denies": 0, "dn_t": null, "firstblood_claimed": null, "gold": null, "gold_per_min": 202, "gold_reasons": null, "gold_spent": null, "gold_t": null, "hero_damage": null, "hero_healing": null, "hero_hits": null, "hero_id": 86, "item_0": 265, "item_1": 42, "item_2": 36, "item_3": 0, "item_4": 232, "item_5": 214, "item_neutral": 357, "item_uses": null, "kill_streaks": null, "killed": null, "killed_by": null, "kills": 2, "kills_log": null, "lane_pos": null, "last_hits": 46, "leaver_status": 0, "level": 16, "lh_t": null, "life_state": null, "max_hero_hit": null, "multi_kills": null, "net_worth": 5519, "obs": null, "obs_left_log": null, "obs_log": null, "obs_placed": null, "party_id": null, "party_size": null, "performance_others": null, "permanent_buffs": null, "pings": null, "pred_vict": null, "purchase": null, "purchase_log": null, "randomed": null, "repicked": null, "roshans_killed": null, "rune_pickups": null, "runes": null, "runes_log": null, "sen": null, "sen_left_log": null, "sen_log": null, "sen_placed": null, "stuns": null, "teamfight_participation": null, "times": null, "tower_damage": null, "towers_killed": null, "xp_per_min": 321, "xp_reasons": null, "xp_t": null, "radiant_win": false, "start_time": 1604721960, "duration": 2360, "cluster": 123, "lobby_type": 7, "game_mode": 22, "is_contributor": false, "patch": 46, "region": 2, "isRadiant": true, "win": 0, "lose": 1, "total_gold": 7945, "total_xp": 12626, "kills_per_min": 0.05084745762711864, "kda": 0, "abandons": 0, "rank_tier": null, "is_subscriber": false, "cosmetics": [], "benchmarks": {"gold_per_min": {"raw": 202, "pct": 0.03488372093023256}, "xp_per_min": {"raw": 321, "pct": 0.11046511627906977}, "kills_per_min": {"raw": 0.05084745762711864, "pct": 0.23255813953488372}, "last_hits_per_min": {"raw": 1.1694915254237288, "pct": 0.14534883720930233}, "hero_damage_per_min": {"raw": 0, "pct": 0.005813953488372093}, "hero_healing_per_min": {"raw": 0, "pct": 0.6627906976744186}, "tower_damage": {}, "stuns_per_min": {"raw": 0, "pct": 0.005813953488372093}, "lhten": {}}}, {"match_id": 5690297880, "player_slot": 4, "ability_targets": null, "ability_upgrades_arr": null, "ability_uses": null, "account_id": 272582844, "actions": null, "additional_units": null, "assists": 6, "backpack_0": 38, "backpack_1": 75, "backpack_2": 0, "backpack_3": null, "buyback_log": null, "camps_stacked": null, "connection_log": null, "creeps_stacked": null, "damage": null, "damage_inflictor": null, "damage_inflictor_received": null, "damage_taken": null, "damage_targets": null, "deaths": 6, "denies": 9, "dn_t": null, "firstblood_claimed": null, "gold": null, "gold_per_min": 533, "gold_reasons": null, "gold_spent": null, "gold_t": null, "hero_damage": null, "hero_healing": null, "hero_hits": null, "hero_id": 35, "item_0": 263, "item_1": 63, "item_2": 75, "item_3": 135, "item_4": 149, "item_5": 166, "item_neutral": 297, "item_uses": null, "kill_streaks": null, "killed": null, "killed_by": null, "kills": 10, "kills_log": null, "lane_pos": null, "last_hits": 288, "leaver_status": 0, "level": 26, "lh_t": null, "life_state": null, "max_hero_hit": null, "multi_kills": null, "net_worth": 18061, "obs": null, "obs_left_log": null, "obs_log": null, "obs_placed": null, "party_id": null, "party_size": null, "performance_others": null, "permanent_buffs": null, "pings": null, "pred_vict": null, "purchase": null, "purchase_log": null, "randomed": null, "repicked": null, "roshans_killed": null, "rune_pickups": null, "runes": null, "runes_log": null, "sen": null, "sen_left_log": null, "sen_log": null, "sen_placed": null, "stuns": null, "teamfight_participation": null, "times": null, "tower_damage": null, "towers_killed": null, "xp_per_min": 838, "xp_reasons": null, "xp_t": null, "personaname": "Soulmate", "name": null, "last_login": null, "radiant_win": false, "start_time": 1604721960, "duration": 2360, "cluster": 123, "lobby_type": 7, "game_mode": 22, "is_contributor": false, "patch": 46, "region": 2, "isRadiant": true, "win": 0, "lose": 1, "total_gold": 20964, "total_xp": 32961, "kills_per_min": 0.2542372881355932, "kda": 2, "abandons": 0, "rank_tier": 51, "is_subscriber": false, "cosmetics": [], "benchmarks": {"gold_per_min": {"raw": 533, "pct": 0.4411764705882353}, "xp_per_min": {"raw": 838, "pct": 0.9411764705882353}, "kills_per_min": {"raw": 0.2542372881355932, "pct": 0.5588235294117647}, "last_hits_per_min": {"raw": 7.322033898305085, "pct": 0.5882352941176471}, "hero_damage_per_min": {"raw": 0, "pct": 0}, "hero_healing_per_min": {"raw": 0, "pct": 0.9705882352941176}, "tower_damage": {}, "stuns_per_min": {"raw": 0, "pct": 0.058823529411764705}, "lhten": {}}}, {"match_id": 5690297880, "player_slot": 128, "ability_targets": null, "ability_upgrades_arr": null, "ability_uses": null, "account_id": null, "actions": null, "additional_units": null, "assists": 28, "backpack_0": 216, "backpack_1": 0, "backpack_2": 0, "backpack_3": null, "buyback_log": null, "camps_stacked": null, "connection_log": null, "creeps_stacked": null, "damage": null, "damage_inflictor": null, "damage_inflictor_received": null, "damage_taken": null, "damage_targets": null, "deaths": 2, "denies": 5, "dn_t": null, "firstblood_claimed": null, "gold": null, "gold_per_min": 624, "gold_reasons": null, "gold_spent": null, "gold_t": null, "hero_damage": null, "hero_healing": null, "hero_hits": null, "hero_id": 22, "item_0": 41, "item_1": 110, "item_2": 232, "item_3": 121, "item_4": 48, "item_5": 108, "item_neutral": 289, "item_uses": null, "kill_streaks": null, "killed": null, "killed_by": null, "kills": 13, "kills_log": null, "lane_pos": null, "last_hits": 270, "leaver_status": 0, "level": 26, "lh_t": null, "life_state": null, "max_hero_hit": null, "multi_kills": null, "net_worth": 21779, "obs": null, "obs_left_log": null, "obs_log": null, "obs_placed": null, "party_id": null, "party_size": null, "performance_others": null, "permanent_buffs": null, "pings": null, "pred_vict": null, "purchase": null, "purchase_log": null, "randomed": null, "repicked": null, "roshans_killed": null, "rune_pickups": null, "runes": null, "runes_log": null, "sen": null, "sen_left_log": null, "sen_log": null, "sen_placed": null, "stuns": null, "teamfight_participation": null, "times": null, "tower_damage": null, "towers_killed": null, "xp_per_min": 845, "xp_reasons": null, "xp_t": null, "radiant_win": false, "start_time": 1604721960, "duration": 2360, "cluster": 123, "lobby_type": 7, "game_mode": 22, "is_contributor": false, "patch": 46, "region": 2, "isRadiant": false, "win": 1, "lose": 0, "total_gold": 24544, "total_xp": 33236, "kills_per_min": 0.3305084745762712, "kda": 13, "abandons": 0, "rank_tier": null, "is_subscriber": false, "cosmetics": [], "benchmarks": {"gold_per_min": {"raw": 624, "pct": 0.8703703703703703}, "xp_per_min": {"raw": 845, "pct": 0.9259259259259259}, "kills_per_min": {"raw": 0.3305084745762712, "pct": 0.8518518518518519}, "last_hits_per_min": {"raw": 6.864406779661017, "pct": 0.7037037037037037}, "hero_damage_per_min": {"raw": 0, "pct": 0}, "hero_healing_per_min": {"raw": 0, "pct": 0.7592592592592593}, "tower_damage": {}, "stuns_per_min": {"raw": 0, "pct": 0}, "lhten": {}}}, {"match_id": 5690297880, "player_slot": 129, "ability_targets": null, "ability_upgrades_arr": null, "ability_uses": null, "account_id": 212715666, "actions": null, "additional_units": null, "assists": 30, "backpack_0": 0, "backpack_1": 0, "backpack_2": 0, "backpack_3": null, "buyback_log": null, "camps_stacked": null, "connection_log": null, "creeps_stacked": null, "damage": null, "damage_inflictor": null, "damage_inflictor_received": null, "damage_taken": null, "damage_targets": null, "deaths": 4, "denies": 6, "dn_t": null, "firstblood_claimed": null, "gold": null, "gold_per_min": 432, "gold_reasons": null, "gold_spent": null, "gold_t": null, "hero_damage": null, "hero_healing": null, "hero_hits": null, "hero_id": 85, "item_0": 108, "item_1": 231, "item_2": 36, "item_3": 127, "item_4": 37, "item_5": 0, "item_neutral": 336, "item_uses": null, "kill_streaks": null, "killed": null, "killed_by": null, "kills": 11, "kills_log": null, "lane_pos": null, "last_hits": 93, "leaver_status": 0, "level": 23, "lh_t": null, "life_state": null, "max_hero_hit": null, "multi_kills": null, "net_worth": 16283, "obs": null, "obs_left_log": null, "obs_log": null, "obs_placed": null, "party_id": null, "party_size": null, "performance_others": null, "permanent_buffs": null, "pings": null, "pred_vict": null, "purchase": null, "purchase_log": null, "randomed": null, "repicked": null, "roshans_killed": null, "rune_pickups": null, "runes": null, "runes_log": null, "sen": null, "sen_left_log": null, "sen_log": null, "sen_placed": null, "stuns": null, "teamfight_participation": null, "times": null, "tower_damage": null, "towers_killed": null, "xp_per_min": 611, "xp_reasons": null, "xp_t": null, "personaname": "Boom!", "name": null, "last_login": "2023-03-14T08:02:03.434Z", "radiant_win": false, "start_time": 1604721960, "duration": 2360, "cluster": 123, "lobby_type": 7, "game_mode": 22, "is_contributor": false, "patch": 46, "region": 2, "isRadiant": false, "win": 1, "lose": 0, "total_gold": 16992, "total_xp": 24032, "kills_per_min": 0.2796610169491525, "kda": 8, "abandons": 0, "rank_tier": 22, "is_subscriber": false, "cosmetics": [], "benchmarks": {"gold_per_min": {"raw": 432, "pct": 0.9565217391304348}, "xp_per_min": {"raw": 611, "pct": 0.9456521739130435}, "kills_per_min": {"raw": 0.2796610169491526, "pct": 0.9565217391304348}, "last_hits_per_min": {"raw": 2.3644067796610173, "pct": 0.8695652173913043}, "hero_damage_per_min": {"raw": 0, "pct": 0.010869565217391304}, "hero_healing_per_min": {"raw": 0, "pct": 0.03260869565217391}, "tower_damage": {}, "stuns_per_min": {"raw": 0, "pct": 0.9456521739130435}, "lhten": {}}}, {"match_id": 5690297880, "player_slot": 130, "ability_targets": null, "ability_upgrades_arr": null, "ability_uses": null, "account_id": null, "actions": null, "additional_units": null, "assists": 21, "backpack_0": 0, "backpack_1": 0, "backpack_2": 0, "backpack_3": null, "buyback_log": null, "camps_stacked": null, "connection_log": null, "creeps_stacked": null, "damage": null, "damage_inflictor": null, "damage_inflictor_received": null, "damage_taken": null, "damage_targets": null, "deaths": 8, "denies": 12, "dn_t": null, "firstblood_claimed": null, "gold": null, "gold_per_min": 352, "gold_reasons": null, "gold_spent": null, "gold_t": null, "hero_damage": null, "hero_healing": null, "hero_hits": null, "hero_id": 97, "item_0": 226, "item_1": 0, "item_2": 102, "item_3": 29, "item_4": 36, "item_5": 1, "item_neutral": 309, "item_uses": null, "kill_streaks": null, "killed": null, "killed_by": null, "kills": 0, "kills_log": null, "lane_pos": null, "last_hits": 106, "leaver_status": 0, "level": 19, "lh_t": null, "life_state": null, "max_hero_hit": null, "multi_kills": null, "net_worth": 11303, "obs": null, "obs_left_log": null, "obs_log": null, "obs_placed": null, "party_id": null, "party_size": null, "performance_others": null, "permanent_buffs": null, "pings": null, "pred_vict": null, "purchase": null, "purchase_log": null, "randomed": null, "repicked": null, "roshans_killed": null, "rune_pickups": null, "runes": null, "runes_log": null, "sen": null, "sen_left_log": null, "sen_log": null, "sen_placed": null, "stuns": null, "teamfight_participation": null, "times": null, "tower_damage": null, "towers_killed": null, "xp_per_min": 457, "xp_reasons": null, "xp_t": null, "radiant_win": false, "start_time": 1604721960, "duration": 2360, "cluster": 123, "lobby_type": 7, "game_mode": 22, "is_contributor": false, "patch": 46, "region": 2, "isRadiant": false, "win": 1, "lose": 0, "total_gold": 13845, "total_xp": 17975, "kda": 2, "abandons": 0, "rank_tier": null, "is_subscriber": false, "cosmetics": [], "benchmarks": {"gold_per_min": {"raw": 352, "pct": 0.2727272727272727}, "xp_per_min": {"raw": 457, "pct": 0.20454545454545456}, "kills_per_min": {"raw": 0, "pct": 0.09090909090909091}, "last_hits_per_min": {"raw": 2.694915254237288, "pct": 0.1590909090909091}, "hero_damage_per_min": {"raw": 0, "pct": 0}, "hero_healing_per_min": {"raw": 0, "pct": 0.6818181818181818}, "tower_damage": {}, "stuns_per_min": {"raw": 0, "pct": 0}, "lhten": {}}}, {"match_id": 5690297880, "player_slot": 131, "ability_targets": null, "ability_upgrades_arr": null, "ability_uses": null, "account_id": 322971203, "actions": null, "additional_units": null, "assists": 27, "backpack_0": 0, "backpack_1": 0, "backpack_2": 0, "backpack_3": null, "buyback_log": null, "camps_stacked": null, "connection_log": null, "creeps_stacked": null, "damage": null, "damage_inflictor": null, "damage_inflictor_received": null, "damage_taken": null, "damage_targets": null, "deaths": 6, "denies": 3, "dn_t": null, "firstblood_claimed": null, "gold": null, "gold_per_min": 350, "gold_reasons": null, "gold_spent": null, "gold_t": null, "hero_damage": null, "hero_healing": null, "hero_hits": null, "hero_id": 27, "item_0": 232, "item_1": 214, "item_2": 254, "item_3": 36, "item_4": 110, "item_5": 42, "item_neutral": 360, "item_uses": null, "kill_streaks": null, "killed": null, "killed_by": null, "kills": 6, "kills_log": null, "lane_pos": null, "last_hits": 61, "leaver_status": 0, "level": 20, "lh_t": null, "life_state": null, "max_hero_hit": null, "multi_kills": null, "net_worth": 10850, "obs": null, "obs_left_log": null, "obs_log": null, "obs_placed": null, "party_id": null, "party_size": null, "performance_others": null, "permanent_buffs": null, "pings": null, "pred_vict": null, "purchase": null, "purchase_log": null, "randomed": null, "repicked": null, "roshans_killed": null, "rune_pickups": null, "runes": null, "runes_log": null, "sen": null, "sen_left_log": null, "sen_log": null, "sen_placed": null, "stuns": null, "teamfight_participation": null, "times": null, "tower_damage": null, "towers_killed": null, "xp_per_min": 474, "xp_reasons": null, "xp_t": null, "personaname": "Bladao", "name": null, "last_login": null, "radiant_win": false, "start_time": 1604721960, "duration": 2360, "cluster": 123, "lobby_type": 7, "game_mode": 22, "is_contributor": false, "patch": 46, "region": 2, "isRadiant": false, "win": 1, "lose": 0, "total_gold": 13766, "total_xp": 18644, "kills_per_min": 0.15254237288135591, "kda": 4, "abandons": 0, "rank_tier": 54, "is_subscriber": false, "cosmetics": [], "benchmarks": {"gold_per_min": {"raw": 350, "pct": 0.6666666666666666}, "xp_per_min": {"raw": 474, "pct": 0.625}, "kills_per_min": {"raw": 0.15254237288135591, "pct": 0.9583333333333334}, "last_hits_per_min": {"raw": 1.5508474576271185, "pct": 0.5416666666666666}, "hero_damage_per_min": {"raw": 0, "pct": 0}, "hero_healing_per_min": {"raw": 0, "pct": 0.75}, "tower_damage": {}, "stuns_per_min": {"raw": 0, "pct": 0}, "lhten": {}}}, {"match_id": 5690297880, "player_slot": 132, "ability_targets": null, "ability_upgrades_arr": null, "ability_uses": null, "account_id": 134209750, "actions": null, "additional_units": null, "assists": 18, "backpack_0": 0, "backpack_1": 0, "backpack_2": 0, "backpack_3": null, "buyback_log": null, "camps_stacked": null, "connection_log": null, "creeps_stacked": null, "damage": null, "damage_inflictor": null, "damage_inflictor_received": null, "damage_taken": null, "damage_targets": null, "deaths": 2, "denies": 8, "dn_t": null, "firstblood_claimed": null, "gold": null, "gold_per_min": 650, "gold_reasons": null, "gold_spent": null, "gold_t": null, "hero_damage": null, "hero_healing": null, "hero_hits": null, "hero_id": 41, "item_0": 108, "item_1": 117, "item_2": 172, "item_3": 154, "item_4": 48, "item_5": 135, "item_neutral": 376, "item_uses": null, "kill_streaks": null, "killed": null, "killed_by": null, "kills": 22, "kills_log": null, "lane_pos": null, "last_hits": 232, "leaver_status": 0, "level": 26, "lh_t": null, "life_state": null, "max_hero_hit": null, "multi_kills": null, "net_worth": 21729, "obs": null, "obs_left_log": null, "obs_log": null, "obs_placed": null, "party_id": null, "party_size": null, "performance_others": null, "permanent_buffs": null, "pings": null, "pred_vict": null, "purchase": null, "purchase_log": null, "randomed": null, "repicked": null, "roshans_killed": null, "rune_pickups": null, "runes": null, "runes_log": null, "sen": null, "sen_left_log": null, "sen_log": null, "sen_placed": null, "stuns": null, "teamfight_participation": null, "times": null, "tower_damage": null, "towers_killed": null, "xp_per_min": 845, "xp_reasons": null, "xp_t": null, "personaname": "g-", "name": null, "last_login": null, "radiant_win": false, "start_time": 1604721960, "duration": 2360, "cluster": 123, "lobby_type": 7, "game_mode": 22, "is_contributor": false, "patch": 46, "region": 2, "isRadiant": false, "win": 1, "lose": 0, "total_gold": 25566, "total_xp": 33236, "kills_per_min": 0.559322033898305, "kda": 13, "abandons": 0, "rank_tier": 54, "is_subscriber": false, "cosmetics": [], "benchmarks": {"gold_per_min": {"raw": 650, "pct": 0.5666666666666667}, "xp_per_min": {"raw": 845, "pct": 0.5666666666666667}, "kills_per_min": {"raw": 0.5593220338983051, "pct": 0.9333333333333333}, "last_hits_per_min": {"raw": 5.898305084745763, "pct": 0.23333333333333334}, "hero_damage_per_min": {"raw": 0, "pct": 0}, "hero_healing_per_min": {"raw": 0, "pct": 1}, "tower_damage": {}, "stuns_per_min": {"raw": 0, "pct": 0}, "lhten": {}}}], "patch": 46, "region": 2}